ctextlib.pyd
ctextlib-1.0.26.dist-info/LICENSE
ctextlib-1.0.26.dist-info/METADATA
ctextlib-1.0.26.dist-info/WHEEL
ctextlib-1.0.26.dist-info/top_level.txt
ctextlib-1.0.26.dist-info/RECORD
