Metadata-Version: 2.1
Name: ctextlib
Version: 1.0.26
Summary: Python package with CText C++ extension
Home-page: https://github.com/antonmilev/CText
Author: Anton Milev
Author-email: amil@abv.bg
License: UNKNOWN
Platform: UNKNOWN
Classifier: Programming Language :: Python :: 3
Classifier: Programming Language :: C++
Classifier: License :: OSI Approved :: MIT License
Classifier: Operating System :: OS Independent
Requires-Python: >=3.5
